takucyrpt/__init__.py
takucyrpt/data.py
takucyrpt-1.0.0.dist-info/METADATA
takucyrpt-1.0.0.dist-info/WHEEL
takucyrpt-1.0.0.dist-info/top_level.txt
takucyrpt-1.0.0.dist-info/RECORD
