Metadata-Version: 2.4
Name: takucyrpt
Version: 1.0.0
Summary: A simple and comprehensive text encryption/decryption library
Home-page: https://github.com/tarun922/takucyrpt
Author: Tarun Kumar
Author-email: Tarun Kumar <tarunkum8800@gmail.com>
License: MIT
Project-URL: Homepage, https://github.com/tarun922/takucyrpt
Project-URL: Bug Reports, https://github.com/tarun922/takucyrpt/issues
Project-URL: Source, https://github.com/tarun922/takucyrpt
Keywords: encryption,decryption,cipher,text,security
Classifier: Development Status :: 4 - Beta
Classifier: Intended Audience :: Developers
Classifier: License :: OSI Approved :: MIT License
Classifier: Operating System :: OS Independent
Classifier: Programming Language :: Python :: 3
Classifier: Programming Language :: Python :: 3.7
Classifier: Programming Language :: Python :: 3.8
Classifier: Programming Language :: Python :: 3.9
Classifier: Programming Language :: Python :: 3.10
Classifier: Programming Language :: Python :: 3.11
Classifier: Topic :: Security :: Cryptography
Classifier: Topic :: Text Processing
Requires-Python: >=3.6
Dynamic: author
Dynamic: home-page
Dynamic: requires-python
